korean_name_generator/namer.py
korean_name_generator/trained_data.py
korean_name_generator-1.0.1.dist-info/LICENSE
korean_name_generator-1.0.1.dist-info/METADATA
korean_name_generator-1.0.1.dist-info/WHEEL
korean_name_generator-1.0.1.dist-info/top_level.txt
korean_name_generator-1.0.1.dist-info/RECORD
