Metadata-Version: 2.1
Name: korean-name-generator
Version: 1.0.1
Summary: Generates random but reasonable Korean names
Home-page: https://github.com/tinyjin/korean-name-generator
Author: Jinui You
Author-email: baram991103@gmail.com
License: MIT
Keywords: Korean
Platform: UNKNOWN
Classifier: Programming Language :: Python :: 3
Classifier: License :: OSI Approved :: MIT License
Classifier: Operating System :: OS Independent
